building2parcel_trainingdata/__init__.py
building2parcel_trainingdata/building2parcel_trainingdata.py
building2parcel_trainingdata/run_mapper.py
building2parcel_trainingdata-0.3.2.dist-info/LICENSE
building2parcel_trainingdata-0.3.2.dist-info/METADATA
building2parcel_trainingdata-0.3.2.dist-info/WHEEL
building2parcel_trainingdata-0.3.2.dist-info/entry_points.txt
building2parcel_trainingdata-0.3.2.dist-info/top_level.txt
building2parcel_trainingdata-0.3.2.dist-info/RECORD
