Metadata-Version: 2.1
Name: building2parcel-trainingdata
Version: 0.3.2
Summary: A package for mapping parcels and buildings using various data sources
Home-page: https://github.com/scalable-design-participation-lab/building2parcel-trainingdata.git
Author: Dezeng Kong
Author-email: kong.dez@northeastern.edu
Classifier: Programming Language :: Python :: 3
Classifier: License :: OSI Approved :: MIT License
Classifier: Operating System :: OS Independent
Requires-Python: >=3.6
License-File: LICENSE
Requires-Dist: matplotlib
Requires-Dist: cartopy
Requires-Dist: geopandas
Requires-Dist: python-dotenv
Requires-Dist: Pillow
Requires-Dist: numpy
Requires-Dist: owslib
Requires-Dist: tqdm
Requires-Dist: pandas
